Workbook

Sheet Instructions
A1: BUSINESS IMPACT ANALYSIS (BIA) WORKBOOK
A2: [Company Name]
A4: Document Reference: | D4: BIA-001
A5: Version: | D5: 1.0
A6: Date Completed: | D6: [DD/MM/YYYY]
A7: Review Date: | D7: [DD/MM/YYYY]
A8: Completed By: | D8: [Name and Job Title]
A9: Approved By: | D9: [Name and Job Title]
A11: HOW TO USE THIS WORKBOOK
A12: This workbook contains 7 working sheets. Complete them in the order shown below:
A13: Tab | D13: Content | F13: Purpose
A14: 1. Instructions | D14: This sheet | F14: Overview of workbook and how to use it
A15: 2. Function Register | D15: List all business functions | F15: Identify and categorise every business process
A16: 3. BIA Assessment | D16: Impact analysis per function | F16: Assess disruption impact and define recovery objectives
A17: 4. Dependency Map | D17: Map critical dependencies | F17: Identify people, systems, suppliers, equipment dependencies
A18: 5. Risk Scenarios | D18: Threat and scenario analysis | F18: Link risks to functions and assess exposure
A19: 6. Recovery Plan | D19: Recovery action cards | F19: Define actions, owners and timescales for each scenario
A20: 7. BIA Summary | D20: Auto-calculated dashboard | F20: RAG summary of all functions, MTD and RTO/RPO totals
A22: KEY DEFINITIONS
A23: MTD - Maximum Tolerable Downtime: | D23: The longest period of time a business function can be unavailable before it causes unacceptable consequences.
A24: RTO - Recovery Time Objective: | D24: The target time within which a business function must be restored after a disruption. Must always be less than the MTD.
A25: RPO - Recovery Point Objective: | D25: The maximum acceptable amount of data loss measured in time. Defines how far back in time you can restore from a backup.
A26: BCP - Business Continuity Plan: | D26: The overarching documented plan setting out how the company will respond to and recover from disruptive incidents.
A27: Critical Function: | D27: Any function whose unavailability for more than 24 hours would cause significant customer, financial, regulatory or safety impact.
A28: Dependency: | D28: Any resource (system, person, supplier, equipment, utility) that a business function requires in order to operate.

Sheet Function Register
A1: BUSINESS FUNCTION REGISTER
A2: List all business functions and processes. Include every activity the company performs, regardless of whether it is currently supported by a documented procedure.
A3: Ref | B3: Business Function | C3: Department | D3: Function Owner | E3: Description / Key Activities | F3: Staffing Level (FTE) | G3: Works Location | H3: Priority (1-Critical, 2-High, 3-Med) | I3: Status | J3: Notes
A4: BF-01 | B4: Sales Order Processing | C4: Sales | D4: [Name] | E4: Receive, process and confirm customer orders via ERP system | F4: 2 | G4: Office | H4: 1 - Critical | I4: Active
A5: BF-02 | B5: CNC Machining - Production | C5: Manufacturing | D5: [Name] | E5: Precision machining of components to drawing specification | F5: 12 | G5: Shop floor | H5: 1 - Critical | I5: Active | J5: Key revenue-generating function
A6: BF-03 | B6: Goods Inward / Inspection | C6: Quality | D6: [Name] | E6: Receive, inspect and certify incoming materials to specification | F6: 2 | G6: Shop floor | H6: 1 - Critical | I6: Active
A7: BF-04 | B7: Quality Control and Inspection | C7: Quality | D7: [Name] | E7: In-process and final inspection of products to customer requirements | F7: 3 | G7: Shop floor | H7: 1 - Critical | I7: Active
A8: BF-05 | B8: Despatch and Logistics | C8: Logistics | D8: [Name] | E8: Pack, label, document and despatch finished goods | F8: 2 | G8: Shop floor | H8: 2 - High | I8: Active
A9: BF-06 | B9: Engineering / Design | C9: Engineering | D9: [Name] | E9: Preparation of drawings, specifications and manufacturing routes | F9: 2 | G9: Office | H9: 2 - High | I9: Active
A10: BF-07 | B10: Customer Service / Account Management | C10: Sales | D10: [Name] | E10: Manage customer enquiries, orders, complaints and relationships | F10: 2 | G10: Office | H10: 2 - High | I10: Active
A11: BF-08 | B11: Finance / Accounts | C11: Finance | D11: [Name] | E11: Purchase ledger, sales ledger, payroll, VAT and management accounts | F11: 2 | G11: Office | H11: 3 - Medium | I11: Active
A12: BF-09 | B12: IT / Systems Administration | C12: IT | D12: [Name] | E12: Maintain network, servers, ERP, email and user access | F12: 1 | G12: Office / Remote | H12: 2 - High | I12: Active
A13: BF-10 | B13: HR / People Management | C13: HR | D13: [Name] | E13: Recruitment, training records, absence management, contracts | F13: 1 | G13: Office | H13: 3 - Medium | I13: Active
A14: BF-11 | B14: Procurement | C14: Manufacturing | D14: [Name] | E14: Source, order and manage suppliers for materials and services | F14: 1 | G14: Office | H14: 2 - High | I14: Active
A15: BF-12 | B15: Health, Safety and Environment | C15: Management | D15: [Name] | E15: QHSE management, audits, risk assessments, incident reporting | F15: 1 | G15: All areas | H15: 2 - High | I15: Active
A16: BF-13 | B16: [Add function]
A17: BF-14 | B17: [Add function]
A18: BF-15 | B18: [Add function]

Sheet BIA Assessment
A1: BUSINESS IMPACT ANALYSIS - FUNCTION ASSESSMENT
A2: For each business function, assess the impact of disruption and define recovery objectives. Use the impact scores (1-5) to reflect severity.
A3: Ref | B3: Business Function | C3: Priority (1-4) | D3: Financial Impact (1-5) | E3: Customer Impact (1-5) | F3: Regulatory Impact (1-5) | G3: Reputational Impact (1-5) | H3: Safety Impact (1-5) | I3: Overall Impact Score | J3: MTD (Max Tolerable Downtime) | K3: RTO (Recovery Time Objective) | L3: RPO (Recovery Point Objective)
A4: SCORING GUIDE: | C4: 1 = Negligible | 2 = Minor | 3 = Moderate | 4 = Significant | 5 = Severe / Catastrophic
A5: BF-01 | B5: Sales Order Processing | C5: 1 | D5: 5 | E5: 5 | F5: 3 | G5: 4 | H5: 1 | I5: =AVERAGE(D5:H5)*2 | J5: 4 hours | K5: 2 hours | L5: 1 hour
A6: BF-02 | B6: CNC Machining - Production | C6: 1 | D6: 5 | E6: 5 | F6: 3 | G6: 4 | H6: 3 | I6: =AVERAGE(D6:H6)*2 | J6: 24 hours | K6: 8 hours | L6: N/A
A7: BF-03 | B7: Goods Inward / Inspection | C7: 1 | D7: 4 | E7: 5 | F7: 4 | G7: 3 | H7: 2 | I7: =AVERAGE(D7:H7)*2 | J7: 24 hours | K7: 8 hours | L7: 4 hours
A8: BF-04 | B8: Quality Control and Inspection | C8: 1 | D8: 4 | E8: 5 | F8: 5 | G8: 4 | H8: 3 | I8: =AVERAGE(D8:H8)*2 | J8: 24 hours | K8: 8 hours | L8: 4 hours
A9: BF-05 | B9: Despatch and Logistics | C9: 2 | D9: 4 | E9: 4 | F9: 2 | G9: 3 | H9: 1 | I9: =AVERAGE(D9:H9)*2 | J9: 24 hours | K9: 8 hours | L9: 1 hour
A10: BF-06 | B10: Engineering / Design | C10: 2 | D10: 3 | E10: 3 | F10: 2 | G10: 3 | H10: 1 | I10: =AVERAGE(D10:H10)*2 | J10: 48 hours | K10: 24 hours | L10: 4 hours
A11: BF-07 | B11: Customer Service / Account Mgmt | C11: 2 | D11: 3 | E11: 4 | F11: 1 | G11: 4 | H11: 1 | I11: =AVERAGE(D11:H11)*2 | J11: 24 hours | K11: 4 hours | L11: 1 hour
A12: BF-08 | B12: Finance / Accounts | C12: 3 | D12: 4 | E12: 2 | F12: 4 | G12: 2 | H12: 1 | I12: =AVERAGE(D12:H12)*2 | J12: 5 days | K12: 2 days | L12: 24 hours
A13: BF-09 | B13: IT / Systems Administration | C13: 2 | D13: 5 | E13: 5 | F13: 3 | G13: 4 | H13: 2 | I13: =AVERAGE(D13:H13)*2 | J13: 8 hours | K13: 4 hours | L13: 1 hour
A14: BF-10 | B14: HR / People Management | C14: 3 | D14: 2 | E14: 2 | F14: 3 | G14: 2 | H14: 1 | I14: =AVERAGE(D14:H14)*2 | J14: 1 week | K14: 2 days | L14: 24 hours
A15: BF-11 | B15: Procurement | C15: 2 | D15: 4 | E15: 4 | F15: 2 | G15: 2 | H15: 1 | I15: =AVERAGE(D15:H15)*2 | J15: 24 hours | K15: 8 hours | L15: 4 hours
A16: BF-12 | B16: Health, Safety and Environment | C16: 2 | D16: 3 | E16: 3 | F16: 5 | G16: 3 | H16: 5 | I16: =AVERAGE(D16:H16)*2 | J16: 24 hours | K16: 4 hours | L16: N/A
A17: [Add function]
A18: [Add function]
A19: [Add function]

Sheet Dependency Map
A1: CRITICAL DEPENDENCY MAPPING
A2: For each critical business function, identify ALL dependencies. A dependency is anything the function needs to operate.
A3: Ref | B3: Business Function | C3: Dependency Type | D3: Dependency Name / Description | E3: Internal / External | F3: Single Point of Failure? | G3: Backup / Workaround Available? | H3: Backup Description | I3: Owner / Supplier | J3: Criticality (1-5) | K3: Notes
A4: BF-01 | B4: Sales Order Processing | C4: IT System | D4: ERP System (e.g. SAP / Sage) | E4: Internal | F4: Yes | G4: Partial | H4: Manual order acknowledgement via spreadsheet (temporary) | I4: [IT Lead] | J4: 5
A5: BF-01 | B5: Sales Order Processing | C5: IT System | D5: Email / Microsoft 365 | E5: External | F5: Yes | G5: Yes | H5: Phone / fax for urgent orders | I5: [IT Lead] | J5: 4
A6: BF-01 | B6: Sales Order Processing | C6: People | D6: Sales order processor | E6: Internal | F6: Yes | G6: Yes | H6: Sales manager can cover short-term | I6: [HR Lead] | J6: 4
A7: BF-02 | B7: CNC Machining - Production | C7: Equipment / Machine | D7: CNC Machining Centre 1 | E7: Internal | F7: Yes | G7: Partial | H7: Subcontract to [Approved Subcontractor] | I7: [Ops Lead] | J7: 5
A8: BF-02 | B8: CNC Machining - Production | C8: Supplier / Material | D8: Billet aluminium supplier | E8: External | F8: No | G8: Yes | H8: Secondary approved supplier available | I8: [Procurement] | J8: 5
A9: BF-02 | B9: CNC Machining - Production | C9: People | D9: CNC setter / operator | E9: Internal | F9: No | G9: Yes | H9: 2 x cross-trained operators | I9: [Ops Lead] | J9: 5
A10: BF-02 | B10: CNC Machining - Production | C10: Utility | D10: Compressed air supply | E10: Internal | F10: Yes | G10: No | H10: No immediate backup - review required | I10: [Facilities] | J10: 5 | K10: SPOF - action required
A11: BF-03 | B11: Goods Inward / Inspection | C11: Equipment / Machine | D11: CMM / measurement equipment | E11: Internal | F11: Yes | G11: Partial | H11: Manual gauging for non-critical dims | I11: [Quality Lead] | J11: 4
A12: BF-04 | B12: Quality Control and Inspection | C12: IT System | D12: Quality management system / ERP | E12: Internal | F12: Yes | G12: Yes | H12: Paper-based inspection records (temporary) | I12: [IT Lead] | J12: 4
A13: BF-04 | B13: Quality Control and Inspection | C13: People | D13: Quality Inspector | E13: Internal | F13: Yes | G13: Yes | H13: Production supervisor can sign off short-term | I13: [Quality Lead] | J13: 5
A14: BF-09 | B14: IT / Systems Administration | C14: IT System | D14: Server / cloud infrastructure | E14: Internal | F14: Yes | G14: Yes | H14: Offsite cloud backup - [Provider / Location] | I14: [IT Lead] | J14: 5 | K14: Backup tested: [Date]
A15: BF-09 | B15: IT / Systems Administration | C15: Utility | D15: Mains power supply | E15: External | F15: Yes | G15: Partial | H15: UPS provides [X hours] bridging capacity | I15: [Facilities] | J15: 5
A16: [Add dependency]
A17: [Add dependency]

Sheet Risk Scenarios
A1: BUSINESS CONTINUITY RISK SCENARIO ASSESSMENT
A2: Score each scenario for Likelihood (1-5) and Impact (1-5). Risk Score = Likelihood x Impact. RAG is calculated automatically.
A3: Ref | B3: Risk Scenario | C3: Category | D3: Functions Affected | E3: Likelihood (1-5) | F3: Impact (1-5) | G3: Risk Score | H3: RAG | I3: Key Controls In Place | J3: Residual Score | K3: Action Required
A4: RS-01 | B4: Fire at main premises | C4: Premises | D4: All | E4: 2 | F4: 5 | G4: =E4*F4 | H4: =IF(G4>=15,"RED",IF(G4>=8,"AMBER","GREEN")) | I4: Fire suppression, evacuation plan, insured | J4: =E4*2 | K4: Verify alternative site readiness annually
A5: RS-02 | B5: Flood or severe weather event | C5: Premises | D5: All | E5: 2 | F5: 4 | G5: =E5*F5 | H5: =IF(G5>=15,"RED",IF(G5>=8,"AMBER","GREEN")) | I5: Site drainage reviewed, remote working possible | J5: =E5*2 | K5: Review flood risk assessment
A6: RS-03 | B6: IT systems failure | C6: Technology | D6: BF-01, 03, 04, 08, 09 | E6: 3 | F6: 5 | G6: =E6*F6 | H6: =IF(G6>=15,"RED",IF(G6>=8,"AMBER","GREEN")) | I6: Daily backups, offsite storage, IT DR plan | J6: =E6*2 | K6: Test IT recovery annually
A7: RS-04 | B7: Cyber attack / ransomware | C7: Technology | D7: BF-01, 03, 04, 08, 09 | E7: 3 | F7: 5 | G7: =E7*F7 | H7: =IF(G7>=15,"RED",IF(G7>=8,"AMBER","GREEN")) | I7: Endpoint security, staff training, patching | J7: =E7*3 | K7: Penetration test recommended
A8: RS-05 | B8: Loss of key management personnel | C8: People | D8: Multiple | E8: 3 | F8: 4 | G8: =E8*F8 | H8: =IF(G8>=15,"RED",IF(G8>=8,"AMBER","GREEN")) | I8: Cross-training, succession planning | J8: =E8*2 | K8: Document all key role knowledge
A9: RS-06 | B9: Mass absence (illness / pandemic) | C9: People | D9: All | E9: 2 | F9: 5 | G9: =E9*F9 | H9: =IF(G9>=15,"RED",IF(G9>=8,"AMBER","GREEN")) | I9: Remote working, staggered shifts, cross-training | J9: =E9*2 | K9: Review pandemic plan annually
A10: RS-07 | B10: Critical machine / equipment failure | C10: Equipment | D10: BF-02, BF-03, BF-04 | E10: 3 | F10: 5 | G10: =E10*F10 | H10: =IF(G10>=15,"RED",IF(G10>=8,"AMBER","GREEN")) | I10: PPM schedule, critical spares held | J10: =E10*2 | K10: Review critical spares register
A11: RS-08 | B11: Critical supplier failure | C11: Supply Chain | D11: BF-02, BF-11 | E11: 3 | F11: 4 | G11: =E11*F11 | H11: =IF(G11>=15,"RED",IF(G11>=8,"AMBER","GREEN")) | I11: Dual-source policy, 4-week safety stock | J11: =E11*2 | K11: Qualify secondary supplier for all A-grade materials
A12: RS-09 | B12: Power failure / utility loss | C12: Utilities | D12: All | E12: 2 | F12: 4 | G12: =E12*F12 | H12: =IF(G12>=15,"RED",IF(G12>=8,"AMBER","GREEN")) | I12: UPS for critical systems, generator on-site | J12: =E12*2 | K12: Test UPS and generator quarterly
A13: RS-10 | B13: Loss of site access (landlord / legal) | C13: Premises | D13: All | E13: 1 | F13: 5 | G13: =E13*F13 | H13: =IF(G13>=15,"RED",IF(G13>=8,"AMBER","GREEN")) | I13: Lease reviewed, alternative site identified | J13: =E13*1 | K13: Review lease terms annually
A14: RS-11 | B14: Loss / corruption of critical data | C14: Technology | D14: BF-01, 04, 08 | E14: 2 | F14: 5 | G14: =E14*F14 | H14: =IF(G14>=15,"RED",IF(G14>=8,"AMBER","GREEN")) | I14: Daily backup, offsite cloud, document control | J14: =E14*2 | K14: Verify backup integrity monthly
A15: RS-12 | B15: Regulatory enforcement action / shutdown | C15: Regulatory | D15: All | E15: 1 | F15: 4 | G15: =E15*F15 | H15: =IF(G15>=15,"RED",IF(G15>=8,"AMBER","GREEN")) | I15: Internal audit programme, external certifications | J15: =E15*1 | K15: Maintain audit schedule
A16: [Add scenario]

Sheet Recovery Plans
A1: RECOVERY ACTION PLANS
A2: Complete a recovery action plan for each HIGH or CRITICAL risk scenario identified in the Risk Scenarios sheet. One plan per scenario.
A3: Ref | B3: Risk Scenario | C3: Functions Affected | D3: Priority Action | E3: Action Owner | F3: Timescale | G3: Resources Required | H3: Workaround / Interim Measure | I3: Recovery Status (Not Started / In Progress / Complete) | J3: Notes
A4: RS-03 | B4: IT Systems Failure | C4: All office / ERP | D4: Isolate affected systems immediately | E4: [IT Lead] | F4: Immediate | G4: IT support contacts, network diagram | H4: Switch to paper-based order/production cards | I4: Not Started
A5: RS-03 | B5: IT Systems Failure | C5: All office / ERP | D5: Assess scope and notify Plan Owner | E5: [IT Lead] | F5: Within 1 hour | G5: Systems inventory | H5: Manual processes activated | I5: Not Started
A6: RS-03 | B6: IT Systems Failure | C6: All office / ERP | D6: Restore from verified clean backup | E6: [IT Lead] | F6: As per RTO | G6: Offsite backup: [Location]. Last verified: [Date] | H6: Continue manual fallback until system confirmed clean | I6: Not Started
A7: RS-03 | B7: IT Systems Failure | C7: All office / ERP | D7: Notify affected customers | E7: [Comms Lead] | F7: Within 4 hours | G7: Customer contact list, email templates | H7: Phone calls for urgent orders | I7: Not Started
A8: RS-07 | B8: Critical Machine Failure | C8: BF-02, BF-04 | D8: Isolate machine. Make safe under LOTO | E8: [H&S Lead] | F8: Immediate | G8: LOTO procedures | H8: Quarantine any in-process work | I8: Not Started
A9: RS-07 | B9: Critical Machine Failure | C9: BF-02, BF-04 | D9: Assess impact on live orders | E9: [Ops Lead] | F9: Within 2 hours | G9: Production schedule | H9: Review order priority list | I9: Not Started
A10: RS-07 | B10: Critical Machine Failure | C10: BF-02, BF-04 | D10: Contact OEM / maintenance provider | E10: [Ops Lead] | F10: Within 2 hours | G10: Critical equipment contacts: [Detail] | H10: Check critical spares register | I10: Not Started
A11: RS-07 | B11: Critical Machine Failure | C11: BF-02, BF-04 | D11: Activate approved subcontractor | E11: [Ops Lead] | F11: Within 4 hours | G11: Approved subcontractor list | H11: Issue emergency purchase order | I11: Not Started
A12: RS-08 | B12: Critical Supplier Failure | C12: BF-02, BF-11 | D12: Confirm scope of supply failure | E12: [Procurement] | F12: Within 4 hours | G12: Supplier contact, purchase orders | H12: Review safety stock levels | I12: Not Started
A13: RS-08 | B13: Critical Supplier Failure | C13: BF-02, BF-11 | D13: Activate secondary approved supplier | E13: [Procurement] | F13: Within 24 hours | G13: Approved supplier list | H13: Issue emergency PO | I13: Not Started
A14: RS-08 | B14: Critical Supplier Failure | C14: BF-02, BF-11 | D14: Revise production schedule | E14: [Ops Lead] | F14: Within 24 hours | G14: Production schedule, order book | H14: Prioritise most critical customer orders | I14: Not Started
A15: [Add action]
A16: [Add action]

Sheet BIA Summary
A1: BIA SUMMARY DASHBOARD
A2: This sheet provides a summary view of all business functions, their criticality, recovery objectives and current risk posture.
A4: CRITICAL FUNCTIONS | D4: HIGH PRIORITY FUNCTIONS
A6: =COUNTIF('BIA Assessment'!C5:C19,"1") | D6: =COUNTIF('BIA Assessment'!C5:C19,"2")
A7: RED RISK SCENARIOS | D7: AMBER RISK SCENARIOS
A9: =COUNTIF('Risk Scenarios'!H4:H16,"RED") | D9: =COUNTIF('Risk Scenarios'!H4:H16,"AMBER")
A11: FUNCTION CRITICALITY SUMMARY
A12: Ref | B12: Business Function | C12: Priority | D12: Overall Impact Score | E12: MTD | F12: RTO | G12: RPO | H12: Action Required
A13: BF-01 | B13: Sales Order Processing | C13: =IF('BIA Assessment'!C5="1","CRITICAL",IF('BIA Assessment'!C5="2","HIGH",IF('BIA Assessment'!C5="3","MEDIUM","LOW"))) | D13: ='BIA Assessment'!I5 | E13: ='BIA Assessment'!J5 | F13: ='BIA Assessment'!K5 | G13: ='BIA Assessment'!L5 | H13: Review IT fallback procedure
A14: BF-02 | B14: CNC Machining - Production | C14: =IF('BIA Assessment'!C6="1","CRITICAL",IF('BIA Assessment'!C6="2","HIGH",IF('BIA Assessment'!C6="3","MEDIUM","LOW"))) | D14: ='BIA Assessment'!I6 | E14: ='BIA Assessment'!J6 | F14: ='BIA Assessment'!K6 | G14: ='BIA Assessment'!L6 | H14: Subcontract fallback to be confirmed
A15: BF-03 | B15: Goods Inward / Inspection | C15: =IF('BIA Assessment'!C7="1","CRITICAL",IF('BIA Assessment'!C7="2","HIGH",IF('BIA Assessment'!C7="3","MEDIUM","LOW"))) | D15: ='BIA Assessment'!I7 | E15: ='BIA Assessment'!J7 | F15: ='BIA Assessment'!K7 | G15: ='BIA Assessment'!L7 | H15: Manual gauging procedure to be tested
A16: BF-04 | B16: Quality Control and Inspection | C16: =IF('BIA Assessment'!C8="1","CRITICAL",IF('BIA Assessment'!C8="2","HIGH",IF('BIA Assessment'!C8="3","MEDIUM","LOW"))) | D16: ='BIA Assessment'!I8 | E16: ='BIA Assessment'!J8 | F16: ='BIA Assessment'!K8 | G16: ='BIA Assessment'!L8 | H16: Paper inspection records tested
A17: BF-05 | B17: Despatch and Logistics | C17: =IF('BIA Assessment'!C9="1","CRITICAL",IF('BIA Assessment'!C9="2","HIGH",IF('BIA Assessment'!C9="3","MEDIUM","LOW"))) | D17: ='BIA Assessment'!I9 | E17: ='BIA Assessment'!J9 | F17: ='BIA Assessment'!K9 | G17: ='BIA Assessment'!L9 | H17: Alternative carrier agreements needed
A18: BF-06 | B18: Engineering / Design | C18: =IF('BIA Assessment'!C10="1","CRITICAL",IF('BIA Assessment'!C10="2","HIGH",IF('BIA Assessment'!C10="3","MEDIUM","LOW"))) | D18: ='BIA Assessment'!I10 | E18: ='BIA Assessment'!J10 | F18: ='BIA Assessment'!K10 | G18: ='BIA Assessment'!L10 | H18: CAD licences - confirm home working
A19: BF-07 | B19: Customer Service | C19: =IF('BIA Assessment'!C11="1","CRITICAL",IF('BIA Assessment'!C11="2","HIGH",IF('BIA Assessment'!C11="3","MEDIUM","LOW"))) | D19: ='BIA Assessment'!I11 | E19: ='BIA Assessment'!J11 | F19: ='BIA Assessment'!K11 | G19: ='BIA Assessment'!L11 | H19: Phone divert tested
A20: BF-08 | B20: Finance / Accounts | C20: =IF('BIA Assessment'!C12="1","CRITICAL",IF('BIA Assessment'!C12="2","HIGH",IF('BIA Assessment'!C12="3","MEDIUM","LOW"))) | D20: ='BIA Assessment'!I12 | E20: ='BIA Assessment'!J12 | F20: ='BIA Assessment'!K12 | G20: ='BIA Assessment'!L12 | H20: Cloud accounting access confirmed
A21: BF-09 | B21: IT / Systems Administration | C21: =IF('BIA Assessment'!C13="1","CRITICAL",IF('BIA Assessment'!C13="2","HIGH",IF('BIA Assessment'!C13="3","MEDIUM","LOW"))) | D21: ='BIA Assessment'!I13 | E21: ='BIA Assessment'!J13 | F21: ='BIA Assessment'!K13 | G21: ='BIA Assessment'!L13 | H21: Backup recovery test overdue
A22: BF-10 | B22: HR / People Management | C22: =IF('BIA Assessment'!C14="1","CRITICAL",IF('BIA Assessment'!C14="2","HIGH",IF('BIA Assessment'!C14="3","MEDIUM","LOW"))) | D22: ='BIA Assessment'!I14 | E22: ='BIA Assessment'!J14 | F22: ='BIA Assessment'!K14 | G22: ='BIA Assessment'!L14
A23: BF-11 | B23: Procurement | C23: =IF('BIA Assessment'!C15="1","CRITICAL",IF('BIA Assessment'!C15="2","HIGH",IF('BIA Assessment'!C15="3","MEDIUM","LOW"))) | D23: ='BIA Assessment'!I15 | E23: ='BIA Assessment'!J15 | F23: ='BIA Assessment'!K15 | G23: ='BIA Assessment'!L15 | H23: Secondary supplier qualification in progress
A24: BF-12 | B24: Health, Safety and Environment | C24: =IF('BIA Assessment'!C16="1","CRITICAL",IF('BIA Assessment'!C16="2","HIGH",IF('BIA Assessment'!C16="3","MEDIUM","LOW"))) | D24: ='BIA Assessment'!I16 | E24: ='BIA Assessment'!J16 | F24: ='BIA Assessment'!K16 | G24: ='BIA Assessment'!L16
